{"inkVersion":21,"root":[["#","^speaker: ","/#","#","^portrait:null ","/#","#","^audio:null","/#","^Bzzzt... bzzzt..","\n","#","^speaker:??? ","/#","#","^portrait:null ","/#","#","^audio:adit","/#","^Selamat pagi rakyat-rakyat Surabaya, semoga rekan semua sehat dan bahagia.","\n","^Seperti yang saudara-saudara ketahui, pada tanggal 17 Agustus, Indonesia telah memproklamasikan kemerdekaan.","\n","^Bung Karno, Bung Hatta, dan rekan-rekan telah berhasil memproklamasikan kebebasan bangsa Indonesia atas aksi penjajahan oleh bangsa lain.","\n","^Oleh karena itu, mari kita jaga status kemerdekaan ini.","\n","^Bersama-sama, menjadi satu, tanah air Indonesia.","\n","^...","\n","^Selanjutnya, mari kita beralih untuk membahas kabar-kabar hangat hari ini...","\n","#","^speaker:null ","/#","#","^portrait:null ","/#","#","^audio:null","/#","^Siaran radio ini kemudian menyampaikan kabar harian yang sedang beredar.","\n","#","^speaker:??? ","/#","#","^portrait:null ","/#","#","^audio:adit","/#","^Selanjutnya terkait Badan Keamanan Rakjat.","\n","^Badan Keamanan Rakjat di kota Surabaya yang telah dibentuk pada tanggal 24 Agustus 1945, yaitu dua minggu yang lalu.","\n","^Hasil rapat yang telah diadakan telah memutuskan untuk memanggil saudara-saudara yang pernah menjadi anggota kepolisian.","\n","^Kami, mengajak para bekas anggota PETA, Heiho, dan lainnya. Untuk bergabung dengan BKR.","\n","^Segera datang ke gedung BKR di Jalan Basuki Rahmat...","\n","#","^speaker: ","/#","#","^portrait:null ","/#","#","^audio:null","/#","^Bzzzzzt.","\n","end",["done",{"#f":5,"#n":"g-0"}],null],"done",{"#f":1}],"listDefs":{}}